{
  "templateId": "comic-books-standard",
  "items": [
    {
      "id": "david-and-goliath",
      "status": "pending",
      "input": {
        "title": "David and Goliath",
        "summary": "A young shepherd boy defeats a giant warrior with faith and a sling",
        "keyMoments": [
          "Goliath challenges Israel",
          "David volunteers to fight",
          "David chooses stones from the stream",
          "David defeats Goliath with a single stone"
        ]
      },
      "completedAt": null
    },
    {
      "id": "noahs-ark",
      "status": "pending",
      "input": {
        "title": "Noah's Ark",
        "summary": "Noah builds an ark to save his family and animals from a great flood",
        "keyMoments": [
          "God tells Noah to build an ark",
          "Animals enter the ark two by two",
          "The great flood covers the earth",
          "The dove returns with an olive branch",
          "Rainbow promise"
        ]
      },
      "completedAt": null
    },
    {
      "id": "jonah-and-the-whale",
      "status": "pending",
      "input": {
        "title": "Jonah and the Whale",
        "summary": "A prophet tries to run from God but learns obedience through a great fish",
        "keyMoments": [
          "Jonah flees on a ship",
          "Storm threatens the sailors",
          "Jonah thrown overboard",
          "Swallowed by great fish",
          "Jonah prays and is released",
          "Jonah preaches to Nineveh"
        ]
      },
      "completedAt": null
    }
  ]
}
